kasmage/__init__.py
kasmage/__main__.py
kasmage/quips.py
kasmage/receipts.py
kasmage/sentry.py
kasmage-0.5.0.dist-info/METADATA
kasmage-0.5.0.dist-info/WHEEL
kasmage-0.5.0.dist-info/entry_points.txt
kasmage-0.5.0.dist-info/licenses/LICENSE
kasmage-0.5.0.dist-info/RECORD
