Metadata-Version: 2.4
Name: kasmage
Version: 0.5.0
Summary: Frog-wizard-themed CLI to monitor Kaspa transactions and save receipts
License: MIT
License-File: LICENSE
Keywords: kaspa,crypto,cli,payments
Author: Ethan Villalobos
Author-email: ethan.villalobos8@gmail.com
Requires-Python: >=3.8,<4.0
Classifier: License :: OSI Approved :: MIT License
Classifier: Programming Language :: Python :: 3
Classifier: Programming Language :: Python :: 3.8
Classifier: Programming Language :: Python :: 3.9
Classifier: Programming Language :: Python :: 3.10
Classifier: Programming Language :: Python :: 3.11
Classifier: Programming Language :: Python :: 3.12
Classifier: Programming Language :: Python :: 3.13
Classifier: Programming Language :: Python :: 3.14
Requires-Dist: packaging (>=24.0)
Requires-Dist: requests (>=2.31,<3.0)
